rgbgeotif/__init__.py
rgbgeotif/rgbgeotif.py
rgbgeotif-2.0a5.dist-info/LICENSE
rgbgeotif-2.0a5.dist-info/METADATA
rgbgeotif-2.0a5.dist-info/WHEEL
rgbgeotif-2.0a5.dist-info/top_level.txt
rgbgeotif-2.0a5.dist-info/RECORD
