Metadata-Version: 2.1
Name: rgbgeotif
Version: 2.0a5
Summary: Convert GeoTif files to array
Home-page: https://github.com/JeanMaximilienCadic
Author: Jean Maximilien Cadic
Author-email: j.cadic@pm.me
License: MIT
Platform: UNKNOWN
Classifier: Programming Language :: Python :: 3.6
Classifier: License :: OSI Approved :: MIT License
Requires-Python: >=3.6
Requires-Dist: rasterio
Requires-Dist: numpy
Requires-Dist: matplotlib
